{
  "resources": [
    {
      "asset_id": "3da3c8cce28ced0ddb080fb9247b2303",
      "public_id": "cld-sample-4",
      "format": "jpg",
      "version": 1669819947,
      "resource_type": "image",
      "type": "upload",
      "created_at": "2022-11-30T14:52:27Z",
      "bytes": 818600,
      "width": 1870,
      "height": 1250,
      "folder": "",
      "url": "http://res.cloudinary.com/dbhuzlv2i/image/upload/v1669819947/cld-sample-4.jpg",
      "secure_url": "https://res.cloudinary.com/dbhuzlv2i/image/upload/v1669819947/cld-sample-4.jpg"
    },
    {
      "asset_id": "659ed0a770fa5e21e69c0788421ec62a",
      "public_id": "cld-sample-5",
      "format": "jpg",
      "version": 1669819947,
      "resource_type": "image",
      "type": "upload",
      "created_at": "2022-11-30T14:52:27Z",
      "bytes": 379132,
      "width": 1870,
      "height": 1250,
      "folder": "",
      "url": "http://res.cloudinary.com/dbhuzlv2i/image/upload/v1669819947/cld-sample-5.jpg",
      "secure_url": "https://res.cloudinary.com/dbhuzlv2i/image/upload/v1669819947/cld-sample-5.jpg"
    },
    {
      "asset_id": "fca66fd55ef882aa2d2e56dc58c12f0b",
      "public_id": "cld-sample-2",
      "format": "jpg",
      "version": 1669819947,
      "resource_type": "image",
      "type": "upload",
      "created_at": "2022-11-30T14:52:27Z",
      "bytes": 592235,
      "width": 1870,
      "height": 1250,
      "folder": "",
      "url": "http://res.cloudinary.com/dbhuzlv2i/image/upload/v1669819947/cld-sample-2.jpg",
      "secure_url": "https://res.cloudinary.com/dbhuzlv2i/image/upload/v1669819947/cld-sample-2.jpg"
    },
    {
      "asset_id": "29ca4c12516299c50b8ad94ab47fc999",
      "public_id": "cld-sample",
      "format": "jpg",
      "version": 1669819947,
      "resource_type": "image",
      "type": "upload",
      "created_at": "2022-11-30T14:52:27Z",
      "bytes": 476846,
      "width": 1870,
      "height": 1250,
      "folder": "",
      "url": "http://res.cloudinary.com/dbhuzlv2i/image/upload/v1669819947/cld-sample.jpg",
      "secure_url": "https://res.cloudinary.com/dbhuzlv2i/image/upload/v1669819947/cld-sample.jpg"
    },
    {
      "asset_id": "1be0905e83a72fd6f15643e0496983e8",
      "public_id": "cld-sample-3",
      "format": "jpg",
      "version": 1669819947,
      "resource_type": "image",
      "type": "upload",
      "created_at": "2022-11-30T14:52:27Z",
      "bytes": 905834,
      "width": 1870,
      "height": 1250,
      "folder": "",
      "url": "http://res.cloudinary.com/dbhuzlv2i/image/upload/v1669819947/cld-sample-3.jpg",
      "secure_url": "https://res.cloudinary.com/dbhuzlv2i/image/upload/v1669819947/cld-sample-3.jpg"
    },
    {
      "asset_id": "f0c36c9e8b7d65b796cf109aeeb3be2d",
      "public_id": "event1_cuq6ep",
      "format": "jpg",
      "version": 1669819705,
      "resource_type": "image",
      "type": "upload",
      "created_at": "2022-11-30T14:48:25Z",
      "bytes": 309518,
      "width": 1920,
      "height": 1280,
      "folder": "",
      "url": "http://res.cloudinary.com/dbhuzlv2i/image/upload/v1669819705/event1_cuq6ep.jpg",
      "secure_url": "https://res.cloudinary.com/dbhuzlv2i/image/upload/v1669819705/event1_cuq6ep.jpg"
    },
    {
      "asset_id": "957bafdf691d3bf230b48da5faedb811",
      "public_id": "samples/landscapes/landscape-panorama",
      "format": "jpg",
      "version": 1666869913,
      "resource_type": "image",
      "type": "upload",
      "created_at": "2022-10-27T11:25:13Z",
      "bytes": 7858062,
      "width": 10906,
      "height": 2349,
      "folder": "samples/landscapes",
      "url": "http://res.cloudinary.com/dbhuzlv2i/image/upload/v1666869913/samples/landscapes/landscape-panorama.jpg",
      "secure_url": "https://res.cloudinary.com/dbhuzlv2i/image/upload/v1666869913/samples/landscapes/landscape-panorama.jpg"
    },
    {
      "asset_id": "ac143a7a7cf73a14e81dfe9cd85274e2",
      "public_id": "samples/animals/kitten-playing",
      "format": "gif",
      "version": 1666869912,
      "resource_type": "image",
      "type": "upload",
      "created_at": "2022-10-27T11:25:12Z",
      "bytes": 6620002,
      "width": 320,
      "height": 180,
      "folder": "samples/animals",
      "url": "http://res.cloudinary.com/dbhuzlv2i/image/upload/v1666869912/samples/animals/kitten-playing.gif",
      "secure_url": "https://res.cloudinary.com/dbhuzlv2i/image/upload/v1666869912/samples/animals/kitten-playing.gif"
    },
    {
      "asset_id": "2fcce15ac383552e5aa1a98e434f21f3",
      "public_id": "samples/landscapes/nature-mountains",
      "format": "jpg",
      "version": 1666869911,
      "resource_type": "image",
      "type": "upload",
      "created_at": "2022-10-27T11:25:11Z",
      "bytes": 3171453,
      "width": 3000,
      "height": 2000,
      "folder": "samples/landscapes",
      "url": "http://res.cloudinary.com/dbhuzlv2i/image/upload/v1666869911/samples/landscapes/nature-mountains.jpg",
      "secure_url": "https://res.cloudinary.com/dbhuzlv2i/image/upload/v1666869911/samples/landscapes/nature-mountains.jpg"
    },
    {
      "asset_id": "5475e7647b3f07055fd187a569842e80",
      "public_id": "samples/cloudinary-group",
      "format": "jpg",
      "version": 1666869911,
      "resource_type": "image",
      "type": "upload",
      "created_at": "2022-10-27T11:25:11Z",
      "bytes": 2856169,
      "width": 3000,
      "height": 1526,
      "folder": "samples",
      "url": "http://res.cloudinary.com/dbhuzlv2i/image/upload/v1666869911/samples/cloudinary-group.jpg",
      "secure_url": "https://res.cloudinary.com/dbhuzlv2i/image/upload/v1666869911/samples/cloudinary-group.jpg"
    }
  ],
  "next_cursor": "24a4b49bff32683af985459ef2d32ed1b5261e976af1d39fb2a24e893fd441fc"
}
